smartarchive/SqlUtil.py
smartarchive/ToolPlugin.py
smartarchive/ZPOpenAILike(1).py
smartarchive/ZPOpenAILike.py
smartarchive/ZPOpenAILikeNew.py
smartarchive/__init__.py
smartarchive/chatServer.py
smartarchive/docServer.py
smartarchive/docServerOpenAI.py
smartarchive/test.py
smartarchive-0.2.dist-info/METADATA
smartarchive-0.2.dist-info/WHEEL
smartarchive-0.2.dist-info/top_level.txt
smartarchive-0.2.dist-info/RECORD
